pyoxigraph/__init__.py
pyoxigraph/__init__.pyi
pyoxigraph/py.typed
pyoxigraph/pyoxigraph.cpython-310-aarch64-linux-gnu.so
pyoxigraph-0.5.4.dist-info/METADATA
pyoxigraph-0.5.4.dist-info/WHEEL
pyoxigraph-0.5.4.dist-info/RECORD
