Metadata-Version: 2.4
Name: pyoxigraph
Version: 0.5.4
Classifier: Development Status :: 3 - Alpha
Classifier: Intended Audience :: Developers
Classifier: License :: OSI Approved :: Apache Software License
Classifier: License :: OSI Approved :: MIT License
Classifier: Programming Language :: Python :: 3 :: Only
Classifier: Programming Language :: Python :: 3.8
Classifier: Programming Language :: Python :: 3.9
Classifier: Programming Language :: Python :: 3.10
Classifier: Programming Language :: Python :: 3.11
Classifier: Programming Language :: Python :: 3.12
Classifier: Programming Language :: Python :: 3.13
Classifier: Programming Language :: Python :: 3.14
Classifier: Programming Language :: Python :: Implementation :: CPython
Classifier: Programming Language :: Python :: Implementation :: PyPy
Classifier: Programming Language :: Rust
Classifier: Topic :: Database :: Database Engines/Servers
Classifier: Topic :: Software Development :: Libraries :: Python Modules
Summary: Python bindings of Oxigraph, a SPARQL database and RDF toolkit
Keywords: RDF,SPARQL,graph-database,database
Home-Page: https://pyoxigraph.readthedocs.io/
Author: Tpt <thomas@pellissier-tanon.fr>
Author-email: Tpt <thomas@pellissier-tanon.fr>
License: MIT OR Apache-2.0
Requires-Python: >=3.8
Project-URL: Changelog, https://github.com/oxigraph/oxigraph/blob/main/CHANGELOG.md
Project-URL: Documentation, https://pyoxigraph.readthedocs.io/
Project-URL: Homepage, https://pyoxigraph.readthedocs.io/
Project-URL: Source, https://github.com/oxigraph/oxigraph/tree/main/python
Project-URL: Tracker, https://github.com/oxigraph/oxigraph/issues
